sentence_models/__init__.py
sentence_models/types.py
sentence_models/util.py
sentence_models-0.1.1.dist-info/LICENSE
sentence_models-0.1.1.dist-info/METADATA
sentence_models-0.1.1.dist-info/WHEEL
sentence_models-0.1.1.dist-info/top_level.txt
sentence_models-0.1.1.dist-info/RECORD
