Metadata-Version: 2.1
Name: sentence-models
Version: 0.1.1
Summary: UNKNOWN
Home-page: UNKNOWN
License: UNKNOWN
Platform: UNKNOWN
Requires-Python: >=3.6
License-File: LICENSE
Requires-Dist: embetter[sentence-tfm]
Requires-Dist: lazylines
Requires-Dist: rich
Requires-Dist: scikit-learn
Requires-Dist: skops
Requires-Dist: spacy
